<?xml version="1.0" encoding="utf-8"?>
<IncrementalBankBuild Version="6" Flags="878078161">
	<Platform GUID="{2BE36473-3EF6-49AD-B4D5-E1F6F69DA460}">
		<Banks>
			<Language ID="0">
				<File Name="Ambience" Hash="1035131898" Timestamp="131208443626381650"/>
				<File Name="CharacterMovement" Hash="1692640579" Timestamp="131208473963887225"/>
				<File Name="ForUnity" Hash="1653709822" Timestamp="131207624706678459"/>
				<File Name="Init" Hash="1718699238" Timestamp="131208451669852265"/>
				<File Name="Weapons" Hash="3118002193" Timestamp="131263433927906949"/>
			</Language>
		</Banks>
		<XMLInfo>
			<Language ID="-1">
				<File Name="" Hash="874136390" Timestamp="131263433928427038"/>
			</Language>
		</XMLInfo>
	</Platform>
	<Platform GUID="{82939D7C-9257-4D6D-A353-2BCBD1876B5C}">
		<Banks>
			<Language ID="0">
				<File Name="Ambience" Hash="1035131898" Timestamp="131208443630957621"/>
				<File Name="CharacterMovement" Hash="1605687964" Timestamp="131208473967266846"/>
				<File Name="ForUnity" Hash="1653709822" Timestamp="131207624707423897"/>
				<File Name="Init" Hash="4238449446" Timestamp="131208451672348418"/>
				<File Name="Weapons" Hash="3118002193" Timestamp="131263433929726607"/>
			</Language>
		</Banks>
		<XMLInfo>
			<Language ID="-1">
				<File Name="" Hash="1935110643" Timestamp="131263433929877130"/>
			</Language>
		</XMLInfo>
	</Platform>
</IncrementalBankBuild>
